MANIFEST.in
README.md
setup.py
cameramodule/__init__.py
cameramodule/camera.py
cameramodule/camerautils.py
cameramodule/flanndetector.py
cameramodule/imageutils.py
classifiers/haarCascadeRoad.xml
classifiers/haarcascade_eye.xml
classifiers/haarcascade_frontalface_default.xml
initializer/__init__.py
initializer/mainloop.py
picameracv.egg-info/PKG-INFO
picameracv.egg-info/SOURCES.txt
picameracv.egg-info/dependency_links.txt
picameracv.egg-info/top_level.txt
signstext/100/100.jpg
signstext/120/120.jpg
signstext/30/30.jpg
signstext/40/40.jpg
signstext/50/50.jpg
signstext/60/60.jpg
signstext/70/70.jpg
signstext/80/80.jpg