Metadata-Version: 1.1
Name: picameracv
Version: 0.5
Summary: Project for picamera/webcamera image processing and pattern detections
Home-page: http://packages.python.org/picameracv
Author: geka
Author-email: geka.kud@gmail.com
License: GNU General Public License (GPL)
Keywords: picamera image processing
Platform: UNKNOWN
Classifier: Development Status :: 3 - Alpha
Classifier: Topic :: Scientific/Engineering :: Image Recognition
Classifier: License :: OSI Approved :: GNU General Public License (GPL)
